generate_html/__init__.py
generate_html/components.py
generate_html/context.py
generate_html/html.py
generate_html/interface.py
generate_html/nodes.py
generate_html-1.0.0.dist-info/LICENSE-APACHE
generate_html-1.0.0.dist-info/LICENSE-MIT
generate_html-1.0.0.dist-info/METADATA
generate_html-1.0.0.dist-info/WHEEL
generate_html-1.0.0.dist-info/top_level.txt
generate_html-1.0.0.dist-info/RECORD
