Metadata-Version: 2.1
Name: generate-html
Version: 1.0.0
Summary: Generate HTML5 with Python generators
Home-page: https://github.com/gvx/generate-html
Author: Jasmijn Wellner
Author-email: gyvox.public@gmail.com
Maintainer: 
Maintainer-email: 
License: MIT/Apache-2.0
Platform: UNKNOWN
Classifier: Development Status :: 4 - Beta
Classifier: Intended Audience :: Developers
Classifier: License :: OSI Approved :: MIT License
Classifier: License :: OSI Approved :: Apache Software License
Classifier: Natural Language :: English
Classifier: Operating System :: OS Independent
Classifier: Programming Language :: Python :: 3.8
Classifier: Programming Language :: Python :: 3.9
Classifier: Programming Language :: Python :: Implementation :: CPython
Classifier: Programming Language :: Python :: Implementation :: PyPy
